telescopus/__init__.py
telescopus/binaries/telescopus.cp313-win_amd64.pyd
telescopus-0.1.0a2.dist-info/LICENSE
telescopus-0.1.0a2.dist-info/METADATA
telescopus-0.1.0a2.dist-info/WHEEL
telescopus-0.1.0a2.dist-info/top_level.txt
telescopus-0.1.0a2.dist-info/RECORD
